emo/__init__.py
emo/loss.py
EMOLoss-0.0.3.dist-info/LICENSE
EMOLoss-0.0.3.dist-info/METADATA
EMOLoss-0.0.3.dist-info/WHEEL
EMOLoss-0.0.3.dist-info/top_level.txt
EMOLoss-0.0.3.dist-info/RECORD
